dj_arp_storm/__init__.py
dj_arp_storm/callbacks.py
dj_arp_storm/command_line.py
dj_arp_storm/dj_arp_storm.py
dj_arp_storm/player.py
dj_arp_storm-1.0b8.dist-info/DESCRIPTION.rst
dj_arp_storm-1.0b8.dist-info/METADATA
dj_arp_storm-1.0b8.dist-info/RECORD
dj_arp_storm-1.0b8.dist-info/WHEEL
dj_arp_storm-1.0b8.dist-info/entry_points.txt
dj_arp_storm-1.0b8.dist-info/metadata.json
dj_arp_storm-1.0b8.dist-info/top_level.txt
