Metadata-Version: 2.0
Name: dj-arp-storm
Version: 1.0b8
Summary: play network traffic as sound
Home-page: https://gitlab.com/LISTERINE/dj_arp_storm
Author: LISTERINE
Author-email: jon@jonathanferretti.com
License: MIT
Keywords: dj_arp_storm
Platform: UNKNOWN
Classifier: Development Status :: 4 - Beta
Classifier: Intended Audience :: Developers
Classifier: License :: OSI Approved :: MIT License
Classifier: Natural Language :: English
Classifier: Programming Language :: Python :: 2
Classifier: Programming Language :: Python :: 2.7
Classifier: Programming Language :: Python :: 3
Classifier: Programming Language :: Python :: 3.6
Requires-Dist: pyshark
Requires-Dist: netifaces
Requires-Dist: pygame
Requires-Dist: configparser
